nn_rag/__init__.py
nn_rag/components/__init__.py
nn_rag/components/abstract_common_component.py
nn_rag/components/agent.py
nn_rag/components/commons.py
nn_rag/components/controller.py
nn_rag/components/discovery.py
nn_rag/components/generator.py
nn_rag/components/knowledge.py
nn_rag/components/retrieval.py
nn_rag/handlers/__init__.py
nn_rag/handlers/chroma_handlers.py
nn_rag/handlers/handler_utilities.py
nn_rag/handlers/knowledge_handlers.py
nn_rag/handlers/milvus_handlers.py
nn_rag/intent/__init__.py
nn_rag/intent/abstract_agent_intent.py
nn_rag/intent/abstract_generator_intent.py
nn_rag/intent/abstract_knowledge_intent.py
nn_rag/intent/abstract_retrieval_intent.py
nn_rag/intent/agent_intent.py
nn_rag/intent/controller_intent.py
nn_rag/intent/generator_intent.py
nn_rag/intent/knowledge_intent.py
nn_rag/intent/retrieval_intent.py
nn_rag/managers/__init__.py
nn_rag/managers/agent_property_manager.py
nn_rag/managers/controller_property_manager.py
nn_rag/managers/generator_property_manager.py
nn_rag/managers/knowledge_property_manager.py
nn_rag/managers/retrieval_property_manager.py
nn_rag/services/__init__.py
nn_rag/services/docker/__init__.py
nn_rag/services/docker/src/__init__.py
nn_rag/services/docker/src/hadron_executor.py
test/__init__.py
test/handlers/__init__.py
test/handlers/chroma_handlers_test.py
test/handlers/knowledge_handlers_test.py
test/handlers/milvus_handlers_test.py
test/intent/__init__.py
test/intent/generator_intent_test.py
test/intent/knowledge_intent_test.py
test/intent/retrieval_intent_test.py
neural_rag-0.5.27.dist-info/LICENSE.txt
neural_rag-0.5.27.dist-info/METADATA
neural_rag-0.5.27.dist-info/WHEEL
neural_rag-0.5.27.dist-info/top_level.txt
neural_rag-0.5.27.dist-info/RECORD
