Metadata-Version: 2.1
Name: neural_rag
Version: 0.5.27
Home-page: http://github.com/gigas64/hadron-nn
Author: Gigas64
Author-email: gigas64@aistac.net
License: MIT
Classifier: Development Status :: 3 - Alpha
Classifier: License :: OSI Approved :: MIT License
Classifier: Intended Audience :: Developers
Classifier: Intended Audience :: Science/Research
Classifier: Programming Language :: Python :: 3.8
Classifier: Programming Language :: Python :: 3.9
Classifier: Programming Language :: Python :: 3.10
Classifier: Programming Language :: Python :: 3.11
Classifier: Topic :: Adaptive Technologies
Classifier: Topic :: Scientific/Engineering :: Artificial Intelligence
Classifier: Topic :: Scientific/Engineering :: Information Analysis
Classifier: Topic :: Software Development :: Libraries :: Python Modules
License-File: LICENSE.txt
Requires-Dist: pyarrow
Requires-Dist: pandas
Requires-Dist: numpy
Requires-Dist: torch
Requires-Dist: requests
Requires-Dist: pymupdf
Requires-Dist: pymupdf4llm
Requires-Dist: sentence-transformers
Requires-Dist: spacy
Requires-Dist: transformers
Requires-Dist: accelerate
Requires-Dist: bitsandbytes
Requires-Dist: wheel
Requires-Dist: tqdm
Requires-Dist: markdown
